instagrapi/__init__.py
instagrapi/config.py
instagrapi/exceptions.py
instagrapi/extractors.py
instagrapi/story.py
instagrapi/types.py
instagrapi/utils.py
instagrapi/zones.py
instagrapi/mixins/__init__.py
instagrapi/mixins/account.py
instagrapi/mixins/album.py
instagrapi/mixins/auth.py
instagrapi/mixins/bloks.py
instagrapi/mixins/challenge.py
instagrapi/mixins/clip.py
instagrapi/mixins/collection.py
instagrapi/mixins/comment.py
instagrapi/mixins/direct.py
instagrapi/mixins/fbsearch.py
instagrapi/mixins/fundraiser.py
instagrapi/mixins/hashtag.py
instagrapi/mixins/highlight.py
instagrapi/mixins/igtv.py
instagrapi/mixins/insights.py
instagrapi/mixins/location.py
instagrapi/mixins/media.py
instagrapi/mixins/multiple_accounts.py
instagrapi/mixins/note.py
instagrapi/mixins/notification.py
instagrapi/mixins/password.py
instagrapi/mixins/photo.py
instagrapi/mixins/private.py
instagrapi/mixins/public.py
instagrapi/mixins/share.py
instagrapi/mixins/story.py
instagrapi/mixins/timeline.py
instagrapi/mixins/totp.py
instagrapi/mixins/track.py
instagrapi/mixins/user.py
instagrapi/mixins/video.py
instagrapi_markatsteps-1.16.41.3.dist-info/LICENSE
instagrapi_markatsteps-1.16.41.3.dist-info/METADATA
instagrapi_markatsteps-1.16.41.3.dist-info/WHEEL
instagrapi_markatsteps-1.16.41.3.dist-info/top_level.txt
instagrapi_markatsteps-1.16.41.3.dist-info/RECORD
